zenlayercloud/__init__.py
zenlayercloud/alarm/__init__.py
zenlayercloud/alarm/v20250307/__init__.py
zenlayercloud/alarm/v20250307/alarm_client.py
zenlayercloud/alarm/v20250307/models.py
zenlayercloud/bmc/__init__.py
zenlayercloud/bmc/v20221120/__init__.py
zenlayercloud/bmc/v20221120/bmc_client.py
zenlayercloud/bmc/v20221120/models.py
zenlayercloud/ccs/__init__.py
zenlayercloud/ccs/v20250901/__init__.py
zenlayercloud/ccs/v20250901/ccs_client.py
zenlayercloud/ccs/v20250901/models.py
zenlayercloud/common/__init__.py
zenlayercloud/common/abstract_client.py
zenlayercloud/common/abstract_model.py
zenlayercloud/common/config.py
zenlayercloud/common/credential.py
zenlayercloud/common/request.py
zenlayercloud/common/response.py
zenlayercloud/common/utils.py
zenlayercloud/common/excpetion/__init__.py
zenlayercloud/common/excpetion/error_code.py
zenlayercloud/common/excpetion/zenlayer_cloud_sdk_exception.py
zenlayercloud/maintenance/__init__.py
zenlayercloud/maintenance/v20250310/__init__.py
zenlayercloud/maintenance/v20250310/maintenance_client.py
zenlayercloud/maintenance/v20250310/models.py
zenlayercloud/pvtdns/__init__.py
zenlayercloud/pvtdns/v20251101/__init__.py
zenlayercloud/pvtdns/v20251101/models.py
zenlayercloud/pvtdns/v20251101/pvtdns_client.py
zenlayercloud/sdn/__init__.py
zenlayercloud/sdn/v20230830/__init__.py
zenlayercloud/sdn/v20230830/models.py
zenlayercloud/sdn/v20230830/sdn_client.py
zenlayercloud/traffic/__init__.py
zenlayercloud/traffic/v20240326/__init__.py
zenlayercloud/traffic/v20240326/models.py
zenlayercloud/traffic/v20240326/traffic_client.py
zenlayercloud/user/__init__.py
zenlayercloud/user/v20240529/__init__.py
zenlayercloud/user/v20240529/models.py
zenlayercloud/user/v20240529/user_client.py
zenlayercloud/vm/__init__.py
zenlayercloud/vm/v20230313/__init__.py
zenlayercloud/vm/v20230313/models.py
zenlayercloud/vm/v20230313/vm_client.py
zenlayercloud/zbc/__init__.py
zenlayercloud/zbc/v20240809/__init__.py
zenlayercloud/zbc/v20240809/models.py
zenlayercloud_sdk_python-2.0.40.dist-info/licenses/LICENSE
zenlayercloud_sdk_python-2.0.40.dist-info/METADATA
zenlayercloud_sdk_python-2.0.40.dist-info/WHEEL
zenlayercloud_sdk_python-2.0.40.dist-info/top_level.txt
zenlayercloud_sdk_python-2.0.40.dist-info/RECORD
