Metadata-Version: 2.4
Name: zenlayercloud-sdk-python
Version: 2.0.40
Summary: Zenlayer Cloud SDK for Python
Home-page: https://github.com/zenlayer/zenlayercloud-sdk-python
Author: Zenlayer Cloud
Maintainer-email: console_api@zenlayer.com
License: Apache License 2.0
Platform: any
Classifier: Development Status :: 5 - Production/Stable
Classifier: Intended Audience :: Developers
Classifier: License :: OSI Approved :: Apache Software License
Classifier: Programming Language :: Python
Classifier: Programming Language :: Python :: 3
Classifier: Programming Language :: Python :: 3.7
Classifier: Programming Language :: Python :: 3.8
Classifier: Programming Language :: Python :: 3.9
Classifier: Programming Language :: Python :: 3.10
License-File: LICENSE
Requires-Dist: requests>=2.27.0
Dynamic: author
Dynamic: classifier
Dynamic: description
Dynamic: home-page
Dynamic: license
Dynamic: license-file
Dynamic: maintainer-email
Dynamic: platform
Dynamic: requires-dist
Dynamic: summary
